test/__init__.py
test/dataapi_test.py
test/token_test.py
xcsc_dataapi/VERSION.txt
xcsc_dataapi/__init__.py
xcsc_dataapi/data/__init__.py
xcsc_dataapi/data/client.py
xcsc_dataapi/data/token.py
xcsc_dataapi/util/__init__.py
xcsc_dataapi/util/sm4_cbc_util.py
xcsc_dataapi/util/unsafe_renegotiation_adapter.py
xcsc_dataapi-1.0.6.dist-info/METADATA
xcsc_dataapi-1.0.6.dist-info/WHEEL
xcsc_dataapi-1.0.6.dist-info/top_level.txt
xcsc_dataapi-1.0.6.dist-info/RECORD
